hippogriff.py
hippogriff-0.0.2.dist-info/METADATA
hippogriff-0.0.2.dist-info/WHEEL
hippogriff-0.0.2.dist-info/licenses/LICENSE
hippogriff-0.0.2.dist-info/RECORD
