Metadata-Version: 2.1
Name: hippogriff
Version: 0.0.2
Author-email: Volodymyr Kyrylov <vol@wilab.org.ua>
License: MIT License
License-File: LICENSE
Classifier: License :: OSI Approved :: MIT License
Classifier: Operating System :: OS Independent
Classifier: Programming Language :: Python :: 3
Requires-Python: >=3.8
Requires-Dist: accelerated-scan
Requires-Dist: flash-attn>=2.3
Requires-Dist: torch>=2.1
